OrglabExt/OrglabExt.py
OrglabExt/_OrglabExt.pyd
OrglabExt/__init__.py
OrglabExt-1.1.2.data/data/LICENSE.txt
OrglabExt-1.1.2.dist-info/LICENSE.txt
OrglabExt-1.1.2.dist-info/METADATA
OrglabExt-1.1.2.dist-info/WHEEL
OrglabExt-1.1.2.dist-info/top_level.txt
OrglabExt-1.1.2.dist-info/RECORD
